grg_sphinx_theme/__init__.py
grg_sphinx_theme/_version.py
grg_sphinx_theme/header.py
grg_sphinx_theme/team.py
grg_sphinx_theme/assets/scripts/index.js
grg_sphinx_theme/tests/test_header.py
grg_sphinx_theme/theme/grg_sphinx_theme/layout.html
grg_sphinx_theme/theme/grg_sphinx_theme/team.html
grg_sphinx_theme/theme/grg_sphinx_theme/theme.conf
grg_sphinx_theme/theme/grg_sphinx_theme/components/contributors.html
grg_sphinx_theme/theme/grg_sphinx_theme/components/footer-sections.html
grg_sphinx_theme/theme/grg_sphinx_theme/components/footer-sign-up.html
grg_sphinx_theme/theme/grg_sphinx_theme/components/navbar-links.html
grg_sphinx_theme/theme/grg_sphinx_theme/sections/footer.html
grg_sphinx_theme/theme/grg_sphinx_theme/sections/header.html
grg_sphinx_theme/theme/grg_sphinx_theme/static/macros.html
grg_sphinx_theme/theme/grg_sphinx_theme/static/scripts/grg-sphinx-theme.js
grg_sphinx_theme/theme/grg_sphinx_theme/static/scripts/components/toctree.js
grg_sphinx_theme/theme/grg_sphinx_theme/static/styles/animations.css
grg_sphinx_theme/theme/grg_sphinx_theme/static/styles/grg-sphinx-theme.css
grg_sphinx_theme/theme/grg_sphinx_theme/static/styles/override.css
grg_sphinx_theme/theme/grg_sphinx_theme/static/styles/variables.css
grg_sphinx_theme/theme/grg_sphinx_theme/static/styles/components/footer.css
grg_sphinx_theme/theme/grg_sphinx_theme/static/styles/components/navbar.css
grg_sphinx_theme/theme/grg_sphinx_theme/static/styles/components/team.css
grg_sphinx_theme/theme/grg_sphinx_theme/static/styles/components/toctree.css
grg_sphinx_theme-0.4.2.dist-info/METADATA
grg_sphinx_theme-0.4.2.dist-info/WHEEL
grg_sphinx_theme-0.4.2.dist-info/entry_points.txt
grg_sphinx_theme-0.4.2.dist-info/licenses/LICENSE
grg_sphinx_theme-0.4.2.dist-info/RECORD
