Metadata-Version: 2.4
Name: grg-sphinx-theme
Version: 0.4.2
Summary: A GRG sphinx theme to use across GRG projects
Project-URL: Homepage, https://github.com/GRG-Projects/grg-sphinx-theme
Project-URL: documentation, https://github.com/GRG-Projects/grg-sphinx-theme/blob/main/README.md
Project-URL: source, https://github.com/GRG-Projects/grg-sphinx-theme
Project-URL: download, https://pypi.org/project/grg-sphinx-theme/#files
Project-URL: tracker, https://github.com/GRG-Projects/grg-sphinx-theme/issues
Author-email: maharshi-gor <grg-l@list.indiana.edu>, skoudoro <grg-l@list.indiana.edu>
Maintainer-email: GRG web team <grg-l@list.indiana.edu>
License: BSD 3-Clause License
License-File: LICENSE
Classifier: Programming Language :: Python :: 3
Classifier: Programming Language :: Python :: 3.8
Classifier: Programming Language :: Python :: 3.9
Classifier: Programming Language :: Python :: 3.10
Classifier: Programming Language :: Python :: 3.11
Requires-Python: >=3.8
Requires-Dist: pydata-sphinx-theme==0.15.4
Requires-Dist: sphinx>=4
Provides-Extra: all
Requires-Dist: build; extra == 'all'
Requires-Dist: codecov; extra == 'all'
Requires-Dist: coverage; extra == 'all'
Requires-Dist: coveralls; extra == 'all'
Requires-Dist: flake8; extra == 'all'
Requires-Dist: gitpython; extra == 'all'
Requires-Dist: isort; extra == 'all'
Requires-Dist: numpydoc; extra == 'all'
Requires-Dist: pytest!=5.3.4; extra == 'all'
Requires-Dist: pytest-cov; extra == 'all'
Requires-Dist: pytest-doctestplus; extra == 'all'
Requires-Dist: pytest-httpserver; extra == 'all'
Requires-Dist: pytest-xdist; extra == 'all'
Requires-Dist: sphinx~=5.3; extra == 'all'
Requires-Dist: texext; extra == 'all'
Requires-Dist: tomli; (python_version < '3.11') and extra == 'all'
Requires-Dist: twine; extra == 'all'
Requires-Dist: wheel; extra == 'all'
Provides-Extra: dev
Requires-Dist: build; extra == 'dev'
Requires-Dist: flake8; extra == 'dev'
Requires-Dist: gitpython; extra == 'dev'
Requires-Dist: isort; extra == 'dev'
Requires-Dist: twine; extra == 'dev'
Requires-Dist: wheel; extra == 'dev'
Provides-Extra: docs
Requires-Dist: numpydoc; extra == 'docs'
Requires-Dist: sphinx~=5.3; extra == 'docs'
Requires-Dist: texext; extra == 'docs'
Requires-Dist: tomli; (python_version < '3.11') and extra == 'docs'
Provides-Extra: style
Requires-Dist: flake8; extra == 'style'
Requires-Dist: isort; extra == 'style'
Provides-Extra: test
Requires-Dist: codecov; extra == 'test'
Requires-Dist: coverage; extra == 'test'
Requires-Dist: coveralls; extra == 'test'
Requires-Dist: pytest!=5.3.4; extra == 'test'
Requires-Dist: pytest-cov; extra == 'test'
Requires-Dist: pytest-doctestplus; extra == 'test'
Requires-Dist: pytest-httpserver; extra == 'test'
Requires-Dist: pytest-xdist; extra == 'test'
